{
  "manifest_version": "1",
  "name": "Decor",
  "namespace": "bh.decor.decormodule",
  "version": "1.2.1",
  "contributors": [
    {
      "name": "Terter",
      "url": "https://github.com/Georgi-Kalkovski",
      "username": "Terter.4125"
    }
  ],
  "description": "Allows players to have a simple decoration previewer for homestead and guild hall. The module uses the images from GW2 Wiki.",
  "dependencies": {
    "bh.blishhud": ">=1.0.0"
  },
  "url": "https://github.com/Georgi-Kalkovski/GW2Decor",
  "location": "https://github.com/blish-hud/bhud-modules/releases/download/bh.decor.decormodule_v1.2.1/bh.decor.decormodule-1.2.1.bhm",
  "hash": "46A0045898899C4FE843EA3095999B1E9D156214C93872B3A3A4033A06A9AC65"
}
