{
  "manifest_version": "1",
  "name": "Maestro",
  "namespace": "Aex.Maestro",
  "version": "2.0.1",
  "contributors": [
    {
      "name": "Aex"
    }
  ],
  "description": "Play music on GW2 instruments from within Blish HUD. Supports harp, piano, lute, and bass with 103 embedded songs.",
  "dependencies": {
    "bh.blishhud": ">=1.2.0"
  },
  "url": "https://github.com/uwponcel/Maestro",
  "location": "https://github.com/blish-hud/bhud-modules/releases/download/aex.maestro_v2.0.1/Aex.Maestro-2.0.1.bhm",
  "hash": "D9DF87BE519DC74F283BED49A66D6D60631D01B4301B618DB042B0ED86F20B36"
}
