{
  "manifest_version": "1",
  "name": "Chat Shorts",
  "namespace": "Nekres.Chat_Shorts",
  "version": "0.3.6",
  "contributors": [
    {
      "name": "Nekres",
      "username": "Nekres.1943"
    }
  ],
  "description": "Allows you to create shortcuts for recurring chat messages.",
  "dependencies": {
    "bh.blishhud": ">=0.11.6"
  },
  "url": "https://github.com/agaertner/Blish-HUD-Modules-Releases",
  "location": "https://github.com/blish-hud/bhud-modules/releases/download/nekres.chat_shorts_v0.3.6/Nekres.Chat_Shorts-0.3.6.bhm",
  "hash": "BC40BDBE90A27835C2908588E7A3874172085473FAB1A5F4D3C5020D7F6433EC"
}
