{
  "manifest_version": "1",
  "name": "Builds Manager",
  "namespace": "Kenedia.Modules.BuildsManager",
  "version": "1.0.12",
  "contributors": [
    {
      "url": "https://github.com/KenediaDev",
      "name": "Kenedia"
    }
  ],
  "description": "A Blish approach to store and share build setups (gear and build) with your friends, guilds and communities. A must have for everyone with a lot of builds!",
  "dependencies": {
    "bh.blishhud": ">=1.2.0"
  },
  "url": "https://github.com/KenediaDev/Kenedia.BlishHUD",
  "location": "https://github.com/blish-hud/bhud-modules/releases/download/kenedia.modules.buildsmanager_v1.0.12/Kenedia.Modules.BuildsManager-1.0.12.bhm",
  "hash": "B43B9993229B003A3395D899877B359C06C101F2AFC7939707D5F4F65409B6F1"
}
