{
  "manifest_version": "1",
  "name": "Mistwar",
  "namespace": "Nekres.Mistwar",
  "version": "0.5.5",
  "contributors": [
    {
      "username": "Nekres.1943",
      "name": "Nekres"
    }
  ],
  "description": "A tactical map for World VS. World to track objectives, their timers and territory control.",
  "dependencies": {
    "bh.blishhud": ">=0.11.6"
  },
  "url": "https://github.com/agaertner/Blish-HUD-Modules-Releases",
  "location": "https://github.com/blish-hud/bhud-modules/releases/download/nekres.mistwar_v0.5.5/Nekres.Mistwar-0.5.5.bhm",
  "hash": "958EA3E81882F267D2A0D891C33AC4262C91E3ECF3BC9A0A22CD896DCD858B28"
}
