{
  "manifest_version": "1",
  "name": "Regions of Tyria",
  "namespace": "Nekres.Regions_Of_Tyria",
  "version": "0.2.1",
  "contributors": [
    {
      "username": "Nekres.1038",
      "name": "Nekres"
    }
  ],
  "description": "Shows the name of the place you are entering.",
  "dependencies": {
    "bh.blishhud": ">=0.7.0"
  },
  "url": "https://github.com/blish-hud/",
  "location": "https://github.com/TybaIt/Blish-HUD-Modules/releases/download/22%2F02%2F2021/Regions.Of.Tyria.bhm",
  "hash": "5AFDDE20543A15B7D078467FA7644F24986A8B65D0D8957BE11F2C7B304A76E9"
}
