{
  "manifest_version": "1",
  "name": "Pathing Category Explorer Plugin",
  "namespace": "Yeh.PathingCategoryExplorerPlugin",
  "version": "0.0.2",
  "contributors": [
    {
      "username": "****",
      "name": "yeh"
    }
  ],
  "description": "Extend the context menu in the Pathing Category Explorer.",
  "dependencies": {
    "bh.community.pathing": ">=1.11.3",
    "bh.blishhud": ">=1.3.0"
  },
  "url": "https://github.com/cy-sp-howard/PathingCategoryExplorerPlugin",
  "location": "https://github.com/blish-hud/bhud-modules/releases/download/yeh.pathingcategoryexplorerplugin_v0.0.2/Yeh.PathingCategoryExplorerPlugin-0.0.2.bhm",
  "hash": "10675A9EB2274CFAAE45061577F2B9D1822DB72E6A15B07CE68DF976A67F7431"
}
