{
  "manifest_version": "1",
  "name": "Pathing",
  "namespace": "bh.community.pathing",
  "version": "1.1.15",
  "contributors": [
    {
      "url": "https://github.com/dlamkins",
      "name": "Freesnow",
      "username": "freesnow.7251"
    }
  ],
  "description": "Display markers and trails in-game.  Supports both .zip and .taco format markers.\n\nCheck out our guide: https://link.blishhud.com/pathingsetup",
  "dependencies": {
    "bh.blishhud": ">=0.11.2"
  },
  "url": "https://github.com/Blish-HUD/Pathing",
  "location": "https://github.com/blish-hud/bhud-modules/releases/download/bh.community.pathing_v1.1.15/bh.community.pathing-1.1.15.bhm",
  "hash": "260695397135AED642B15862FC1FA70231F889AF793AD3570CF107B411505ABD"
}
