{
  "manifest_version": "1",
  "name": "Pathing",
  "namespace": "bh.community.pathing",
  "version": "1.2.7",
  "contributors": [
    {
      "url": "https://github.com/dlamkins",
      "username": "freesnow.7251",
      "name": "Freesnow"
    }
  ],
  "description": "Display markers and trails in-game.  Supports both .zip and .taco format markers.\n\nCheck out our guide: https://link.blishhud.com/pathingsetup",
  "dependencies": {
    "bh.blishhud": ">=1.0.0"
  },
  "url": "https://github.com/Blish-HUD/Pathing",
  "location": "https://github.com/blish-hud/bhud-modules/releases/download/bh.community.pathing_v1.2.7/bh.community.pathing-1.2.7.bhm",
  "hash": "F6B6514DC20F5EA6D8BE5051CCCB55220FEC6FD941252F279BEC85EF77B26DE5"
}
