{
  "manifest_version": "1",
  "name": "Universal Search",
  "namespace": "bh.general.universalsearch",
  "version": "0.9.0",
  "contributors": [
    {
      "name": "Estreya",
      "username": "Estreya.8675"
    }
  ],
  "description": "Allows you to search for in game landmarks (waypoints, POIs, vistas, etc.), skills and traits and copy the chat codes into your clipboard or directly into the ingame chat.",
  "dependencies": {
    "bh.blishhud": "^1.0.0"
  },
  "url": "https://github.com/Tharylia/Blish-HUD-Modules",
  "location": "https://github.com/blish-hud/bhud-modules/releases/download/bh.general.universalsearch_v0.9.0/bh.general.universalsearch-0.9.0.bhm",
  "hash": "F50682D251BE1557567679A12FB9025DE3E219CBC9AEA48FA7DCF0205EED97EA"
}
